scanner.py
scanoss/__init__.py
scanoss/scanner.py
scanoss_scanner-1.7.3.dist-info/LICENSE
scanoss_scanner-1.7.3.dist-info/METADATA
scanoss_scanner-1.7.3.dist-info/WHEEL
scanoss_scanner-1.7.3.dist-info/entry_points.txt
scanoss_scanner-1.7.3.dist-info/top_level.txt
scanoss_scanner-1.7.3.dist-info/RECORD
