Metadata-Version: 2.1
Name: scanoss-scanner
Version: 1.7.3
Summary: Simple Python library to use the SCANOSS API.
Home-page: UNKNOWN
Author: SCANOSS
Author-email: info@scanoss.com
License: UNKNOWN
Platform: UNKNOWN
Classifier: Programming Language :: Python :: 3
Classifier: Operating System :: OS Independent
Requires-Python: >=3.5
Requires-Dist: requests
Requires-Dist: crc32c
